httpmdhtml/__init__.py
httpmdhtml/md_to_html.py
httpmdhtml/server.py
httpmdhtml-0.1.4.dist-info/LICENSE.txt
httpmdhtml-0.1.4.dist-info/METADATA
httpmdhtml-0.1.4.dist-info/WHEEL
httpmdhtml-0.1.4.dist-info/top_level.txt
httpmdhtml-0.1.4.dist-info/RECORD
