Metadata-Version: 2.1
Name: httpmdhtml
Version: 0.1.4
Summary: HTTP server that converts markdown to HTML
Home-page: https://github.com/treatmesubj/python-md-to-html-server
Download-URL: https://github.com/treatmesubj/python-md-to-html-server/archive/refs/tags/v0.1.4.tar.gz
Author: John Hupperts
Author-email: jrock4503@hotmail.com
License: gpl-3.0
Project-URL: Source, https://github.com/treatmesubj/python-md-to-html-server
License-File: LICENSE.txt
Requires-Dist: markdown-it-py
Requires-Dist: beautifulsoup4
Requires-Dist: html5lib
